README.rst
setup.py
Bottle_Cuturl.egg-info/PKG-INFO
Bottle_Cuturl.egg-info/SOURCES.txt
Bottle_Cuturl.egg-info/dependency_links.txt
Bottle_Cuturl.egg-info/requires.txt
Bottle_Cuturl.egg-info/top_level.txt
app/__init__.py
app/routes.py
app/settings.py
app/assets/jquery/js/jquery-1.11.3.min.js
app/assets/skeletoncss/css/normalize.css
app/assets/skeletoncss/css/skeleton.css
app/controllers/__init__.py
app/controllers/home.py
app/controllers/list.py
app/models/__init__.py
app/models/link.py
app/views/base.html
app/views/index.html
app/views/list.html
app/views/single.html