Metadata-Version: 1.1
Name: Bottle-Cuturl
Version: 0.0.21
Summary: A simple URL Shortener
Home-page: http://github.com/bartgo/bottle-cuturl
Author: BartGo
Author-email: bartoszgo@poczta.onet.pl
License: MIT
Download-URL: https://github.com/bartgo/bottle-cuturl/tarball/v0.0.21
Keywords: url shortener python bottle
Platform: any
Classifier: Development Status :: 1 - Planning
Classifier: License :: OSI Approved :: MIT License
Classifier: Framework :: Bottle
Classifier: Programming Language :: Python
